{"nodes": [{"id": "page_embedtool", "label": "EmbedTool", "file_type": "code", "source_file": "src/app/dashboard/embed/page.tsx", "source_location": null, "source_url": null, "captured_at": null, "author": null, "contributor": null, "rationale": "Interactive wizard to configure clip overlay embeds, generating iframe snippets while checking Pro status to toggle Clipify branding options."}], "edges": [{"source": "page_embedtool", "target": "page_overlaysettings", "relation": "conceptually_related_to", "confidence": "INFERRED", "confidence_score": 0.95, "source_file": "src/app/dashboard/embed/page.tsx", "source_location": null, "weight": 1.0}, {"source": "page_embedtool", "target": "page_dashboard", "relation": "conceptually_related_to", "confidence": "INFERRED", "confidence_score": 0.85, "source_file": "src/app/dashboard/embed/page.tsx", "source_location": null, "weight": 1.0}], "hyperedges": []}