{"nodes": [{"id": "c_coding_thedannicraft_clipify_heroui_docs_migration_meta_json", "label": "meta.json", "file_type": "code", "source_file": "C:\\Coding\\TheDanniCraft-clipify\\.heroui-docs\\migration\\meta.json", "source_location": "L1"}, {"id": "migration_meta_title", "label": "title", "file_type": "code", "source_file": "C:\\Coding\\TheDanniCraft-clipify\\.heroui-docs\\migration\\meta.json", "source_location": "L2"}, {"id": "migration_meta_description", "label": "description", "file_type": "code", "source_file": "C:\\Coding\\TheDanniCraft-clipify\\.heroui-docs\\migration\\meta.json", "source_location": "L3"}, {"id": "migration_meta_root", "label": "root", "file_type": "code", "source_file": "C:\\Coding\\TheDanniCraft-clipify\\.heroui-docs\\migration\\meta.json", "source_location": "L4"}, {"id": "migration_meta_icon", "label": "icon", "file_type": "code", "source_file": "C:\\Coding\\TheDanniCraft-clipify\\.heroui-docs\\migration\\meta.json", "source_location": "L5"}, {"id": "migration_meta_pages", "label": "pages", "file_type": "code", "source_file": "C:\\Coding\\TheDanniCraft-clipify\\.heroui-docs\\migration\\meta.json", "source_location": "L6"}], "edges": [{"source": "c_coding_thedannicraft_clipify_heroui_docs_migration_meta_json", "target": "migration_meta_title", "relation": "contains", "confidence": "EXTRACTED", "source_file": "C:\\Coding\\TheDanniCraft-clipify\\.heroui-docs\\migration\\meta.json", "source_location": "L2", "weight": 1.0}, {"source": "c_coding_thedannicraft_clipify_heroui_docs_migration_meta_json", "target": "migration_meta_description", "relation": "contains", "confidence": "EXTRACTED", "source_file": "C:\\Coding\\TheDanniCraft-clipify\\.heroui-docs\\migration\\meta.json", "source_location": "L3", "weight": 1.0}, {"source": "c_coding_thedannicraft_clipify_heroui_docs_migration_meta_json", "target": "migration_meta_root", "relation": "contains", "confidence": "EXTRACTED", "source_file": "C:\\Coding\\TheDanniCraft-clipify\\.heroui-docs\\migration\\meta.json", "source_location": "L4", "weight": 1.0}, {"source": "c_coding_thedannicraft_clipify_heroui_docs_migration_meta_json", "target": "migration_meta_icon", "relation": "contains", "confidence": "EXTRACTED", "source_file": "C:\\Coding\\TheDanniCraft-clipify\\.heroui-docs\\migration\\meta.json", "source_location": "L5", "weight": 1.0}, {"source": "c_coding_thedannicraft_clipify_heroui_docs_migration_meta_json", "target": "migration_meta_pages", "relation": "contains", "confidence": "EXTRACTED", "source_file": "C:\\Coding\\TheDanniCraft-clipify\\.heroui-docs\\migration\\meta.json", "source_location": "L6", "weight": 1.0}, {"source": "migration_meta_pages", "target": "ref_overview", "relation": "extends", "confidence": "EXTRACTED", "source_file": "C:\\Coding\\TheDanniCraft-clipify\\.heroui-docs\\migration\\meta.json", "source_location": "L6", "weight": 1.0, "context": "import"}, {"source": "migration_meta_pages", "target": "ref_index", "relation": "extends", "confidence": "EXTRACTED", "source_file": "C:\\Coding\\TheDanniCraft-clipify\\.heroui-docs\\migration\\meta.json", "source_location": "L6", "weight": 1.0, "context": "import"}, {"source": "migration_meta_pages", "target": "ref_migration_for_agents", "relation": "extends", "confidence": "EXTRACTED", "source_file": "C:\\Coding\\TheDanniCraft-clipify\\.heroui-docs\\migration\\meta.json", "source_location": "L6", "weight": 1.0, "context": "import"}, {"source": "migration_meta_pages", "target": "ref_migration_for_agents_mcp_server", "relation": "extends", "confidence": "EXTRACTED", "source_file": "C:\\Coding\\TheDanniCraft-clipify\\.heroui-docs\\migration\\meta.json", "source_location": "L6", "weight": 1.0, "context": "import"}, {"source": "migration_meta_pages", "target": "ref_migration_for_agents_agent_skills", "relation": "extends", "confidence": "EXTRACTED", "source_file": "C:\\Coding\\TheDanniCraft-clipify\\.heroui-docs\\migration\\meta.json", "source_location": "L6", "weight": 1.0, "context": "import"}, {"source": "migration_meta_pages", "target": "ref_migration_for_agents_agents_md", "relation": "extends", "confidence": "EXTRACTED", "source_file": "C:\\Coding\\TheDanniCraft-clipify\\.heroui-docs\\migration\\meta.json", "source_location": "L6", "weight": 1.0, "context": "import"}, {"source": "migration_meta_pages", "target": "ref_workflows", "relation": "extends", "confidence": "EXTRACTED", "source_file": "C:\\Coding\\TheDanniCraft-clipify\\.heroui-docs\\migration\\meta.json", "source_location": "L6", "weight": 1.0, "context": "import"}, {"source": "migration_meta_pages", "target": "ref_workflows_full_migration", "relation": "extends", "confidence": "EXTRACTED", "source_file": "C:\\Coding\\TheDanniCraft-clipify\\.heroui-docs\\migration\\meta.json", "source_location": "L6", "weight": 1.0, "context": "import"}, {"source": "migration_meta_pages", "target": "ref_workflows_incremental_migration", "relation": "extends", "confidence": "EXTRACTED", "source_file": "C:\\Coding\\TheDanniCraft-clipify\\.heroui-docs\\migration\\meta.json", "source_location": "L6", "weight": 1.0, "context": "import"}, {"source": "migration_meta_pages", "target": "ref_references", "relation": "extends", "confidence": "EXTRACTED", "source_file": "C:\\Coding\\TheDanniCraft-clipify\\.heroui-docs\\migration\\meta.json", "source_location": "L6", "weight": 1.0, "context": "import"}, {"source": "migration_meta_pages", "target": "ref_hooks", "relation": "extends", "confidence": "EXTRACTED", "source_file": "C:\\Coding\\TheDanniCraft-clipify\\.heroui-docs\\migration\\meta.json", "source_location": "L6", "weight": 1.0, "context": "import"}, {"source": "migration_meta_pages", "target": "ref_styling", "relation": "extends", "confidence": "EXTRACTED", "source_file": "C:\\Coding\\TheDanniCraft-clipify\\.heroui-docs\\migration\\meta.json", "source_location": "L6", "weight": 1.0, "context": "import"}, {"source": "migration_meta_pages", "target": "ref_components", "relation": "extends", "confidence": "EXTRACTED", "source_file": "C:\\Coding\\TheDanniCraft-clipify\\.heroui-docs\\migration\\meta.json", "source_location": "L6", "weight": 1.0, "context": "import"}, {"source": "migration_meta_pages", "target": "ref_components_accordion", "relation": "extends", "confidence": "EXTRACTED", "source_file": "C:\\Coding\\TheDanniCraft-clipify\\.heroui-docs\\migration\\meta.json", "source_location": "L6", "weight": 1.0, "context": "import"}, {"source": "migration_meta_pages", "target": "ref_components_alert", "relation": "extends", "confidence": "EXTRACTED", "source_file": "C:\\Coding\\TheDanniCraft-clipify\\.heroui-docs\\migration\\meta.json", "source_location": "L6", "weight": 1.0, "context": "import"}, {"source": "migration_meta_pages", "target": "ref_components_autocomplete", "relation": "extends", "confidence": "EXTRACTED", "source_file": "C:\\Coding\\TheDanniCraft-clipify\\.heroui-docs\\migration\\meta.json", "source_location": "L6", "weight": 1.0, "context": "import"}, {"source": "migration_meta_pages", "target": "ref_components_avatar", "relation": "extends", "confidence": "EXTRACTED", "source_file": "C:\\Coding\\TheDanniCraft-clipify\\.heroui-docs\\migration\\meta.json", "source_location": "L6", "weight": 1.0, "context": "import"}, {"source": "migration_meta_pages", "target": "ref_components_badge", "relation": "extends", "confidence": "EXTRACTED", "source_file": "C:\\Coding\\TheDanniCraft-clipify\\.heroui-docs\\migration\\meta.json", "source_location": "L6", "weight": 1.0, "context": "import"}, {"source": "migration_meta_pages", "target": "ref_components_breadcrumbs", "relation": "extends", "confidence": "EXTRACTED", "source_file": "C:\\Coding\\TheDanniCraft-clipify\\.heroui-docs\\migration\\meta.json", "source_location": "L6", "weight": 1.0, "context": "import"}, {"source": "migration_meta_pages", "target": "ref_components_calendar", "relation": "extends", "confidence": "EXTRACTED", "source_file": "C:\\Coding\\TheDanniCraft-clipify\\.heroui-docs\\migration\\meta.json", "source_location": "L6", "weight": 1.0, "context": "import"}, {"source": "migration_meta_pages", "target": "ref_components_button", "relation": "extends", "confidence": "EXTRACTED", "source_file": "C:\\Coding\\TheDanniCraft-clipify\\.heroui-docs\\migration\\meta.json", "source_location": "L6", "weight": 1.0, "context": "import"}, {"source": "migration_meta_pages", "target": "ref_components_button_group", "relation": "extends", "confidence": "EXTRACTED", "source_file": "C:\\Coding\\TheDanniCraft-clipify\\.heroui-docs\\migration\\meta.json", "source_location": "L6", "weight": 1.0, "context": "import"}, {"source": "migration_meta_pages", "target": "ref_components_card", "relation": "extends", "confidence": "EXTRACTED", "source_file": "C:\\Coding\\TheDanniCraft-clipify\\.heroui-docs\\migration\\meta.json", "source_location": "L6", "weight": 1.0, "context": "import"}, {"source": "migration_meta_pages", "target": "ref_components_checkbox", "relation": "extends", "confidence": "EXTRACTED", "source_file": "C:\\Coding\\TheDanniCraft-clipify\\.heroui-docs\\migration\\meta.json", "source_location": "L6", "weight": 1.0, "context": "import"}, {"source": "migration_meta_pages", "target": "ref_components_checkbox_group", "relation": "extends", "confidence": "EXTRACTED", "source_file": "C:\\Coding\\TheDanniCraft-clipify\\.heroui-docs\\migration\\meta.json", "source_location": "L6", "weight": 1.0, "context": "import"}, {"source": "migration_meta_pages", "target": "ref_components_chip", "relation": "extends", "confidence": "EXTRACTED", "source_file": "C:\\Coding\\TheDanniCraft-clipify\\.heroui-docs\\migration\\meta.json", "source_location": "L6", "weight": 1.0, "context": "import"}, {"source": "migration_meta_pages", "target": "ref_components_code", "relation": "extends", "confidence": "EXTRACTED", "source_file": "C:\\Coding\\TheDanniCraft-clipify\\.heroui-docs\\migration\\meta.json", "source_location": "L6", "weight": 1.0, "context": "import"}, {"source": "migration_meta_pages", "target": "ref_components_date_picker", "relation": "extends", "confidence": "EXTRACTED", "source_file": "C:\\Coding\\TheDanniCraft-clipify\\.heroui-docs\\migration\\meta.json", "source_location": "L6", "weight": 1.0, "context": "import"}, {"source": "migration_meta_pages", "target": "ref_components_date_range_picker", "relation": "extends", "confidence": "EXTRACTED", "source_file": "C:\\Coding\\TheDanniCraft-clipify\\.heroui-docs\\migration\\meta.json", "source_location": "L6", "weight": 1.0, "context": "import"}, {"source": "migration_meta_pages", "target": "ref_components_divider", "relation": "extends", "confidence": "EXTRACTED", "source_file": "C:\\Coding\\TheDanniCraft-clipify\\.heroui-docs\\migration\\meta.json", "source_location": "L6", "weight": 1.0, "context": "import"}, {"source": "migration_meta_pages", "target": "ref_components_drawer", "relation": "extends", "confidence": "EXTRACTED", "source_file": "C:\\Coding\\TheDanniCraft-clipify\\.heroui-docs\\migration\\meta.json", "source_location": "L6", "weight": 1.0, "context": "import"}, {"source": "migration_meta_pages", "target": "ref_components_dropdown", "relation": "extends", "confidence": "EXTRACTED", "source_file": "C:\\Coding\\TheDanniCraft-clipify\\.heroui-docs\\migration\\meta.json", "source_location": "L6", "weight": 1.0, "context": "import"}, {"source": "migration_meta_pages", "target": "ref_components_form", "relation": "extends", "confidence": "EXTRACTED", "source_file": "C:\\Coding\\TheDanniCraft-clipify\\.heroui-docs\\migration\\meta.json", "source_location": "L6", "weight": 1.0, "context": "import"}, {"source": "migration_meta_pages", "target": "ref_components_image", "relation": "extends", "confidence": "EXTRACTED", "source_file": "C:\\Coding\\TheDanniCraft-clipify\\.heroui-docs\\migration\\meta.json", "source_location": "L6", "weight": 1.0, "context": "import"}, {"source": "migration_meta_pages", "target": "ref_components_input", "relation": "extends", "confidence": "EXTRACTED", "source_file": "C:\\Coding\\TheDanniCraft-clipify\\.heroui-docs\\migration\\meta.json", "source_location": "L6", "weight": 1.0, "context": "import"}, {"source": "migration_meta_pages", "target": "ref_components_input_otp", "relation": "extends", "confidence": "EXTRACTED", "source_file": "C:\\Coding\\TheDanniCraft-clipify\\.heroui-docs\\migration\\meta.json", "source_location": "L6", "weight": 1.0, "context": "import"}, {"source": "migration_meta_pages", "target": "ref_components_kbd", "relation": "extends", "confidence": "EXTRACTED", "source_file": "C:\\Coding\\TheDanniCraft-clipify\\.heroui-docs\\migration\\meta.json", "source_location": "L6", "weight": 1.0, "context": "import"}, {"source": "migration_meta_pages", "target": "ref_components_link", "relation": "extends", "confidence": "EXTRACTED", "source_file": "C:\\Coding\\TheDanniCraft-clipify\\.heroui-docs\\migration\\meta.json", "source_location": "L6", "weight": 1.0, "context": "import"}, {"source": "migration_meta_pages", "target": "ref_components_listbox", "relation": "extends", "confidence": "EXTRACTED", "source_file": "C:\\Coding\\TheDanniCraft-clipify\\.heroui-docs\\migration\\meta.json", "source_location": "L6", "weight": 1.0, "context": "import"}, {"source": "migration_meta_pages", "target": "ref_components_modal", "relation": "extends", "confidence": "EXTRACTED", "source_file": "C:\\Coding\\TheDanniCraft-clipify\\.heroui-docs\\migration\\meta.json", "source_location": "L6", "weight": 1.0, "context": "import"}, {"source": "migration_meta_pages", "target": "ref_components_navbar", "relation": "extends", "confidence": "EXTRACTED", "source_file": "C:\\Coding\\TheDanniCraft-clipify\\.heroui-docs\\migration\\meta.json", "source_location": "L6", "weight": 1.0, "context": "import"}, {"source": "migration_meta_pages", "target": "ref_components_numberinput", "relation": "extends", "confidence": "EXTRACTED", "source_file": "C:\\Coding\\TheDanniCraft-clipify\\.heroui-docs\\migration\\meta.json", "source_location": "L6", "weight": 1.0, "context": "import"}, {"source": "migration_meta_pages", "target": "ref_components_pagination", "relation": "extends", "confidence": "EXTRACTED", "source_file": "C:\\Coding\\TheDanniCraft-clipify\\.heroui-docs\\migration\\meta.json", "source_location": "L6", "weight": 1.0, "context": "import"}, {"source": "migration_meta_pages", "target": "ref_components_popover", "relation": "extends", "confidence": "EXTRACTED", "source_file": "C:\\Coding\\TheDanniCraft-clipify\\.heroui-docs\\migration\\meta.json", "source_location": "L6", "weight": 1.0, "context": "import"}, {"source": "migration_meta_pages", "target": "ref_components_progress", "relation": "extends", "confidence": "EXTRACTED", "source_file": "C:\\Coding\\TheDanniCraft-clipify\\.heroui-docs\\migration\\meta.json", "source_location": "L6", "weight": 1.0, "context": "import"}, {"source": "migration_meta_pages", "target": "ref_components_circular_progress", "relation": "extends", "confidence": "EXTRACTED", "source_file": "C:\\Coding\\TheDanniCraft-clipify\\.heroui-docs\\migration\\meta.json", "source_location": "L6", "weight": 1.0, "context": "import"}, {"source": "migration_meta_pages", "target": "ref_components_radio", "relation": "extends", "confidence": "EXTRACTED", "source_file": "C:\\Coding\\TheDanniCraft-clipify\\.heroui-docs\\migration\\meta.json", "source_location": "L6", "weight": 1.0, "context": "import"}, {"source": "migration_meta_pages", "target": "ref_components_range_calendar", "relation": "extends", "confidence": "EXTRACTED", "source_file": "C:\\Coding\\TheDanniCraft-clipify\\.heroui-docs\\migration\\meta.json", "source_location": "L6", "weight": 1.0, "context": "import"}, {"source": "migration_meta_pages", "target": "ref_components_radio_group", "relation": "extends", "confidence": "EXTRACTED", "source_file": "C:\\Coding\\TheDanniCraft-clipify\\.heroui-docs\\migration\\meta.json", "source_location": "L6", "weight": 1.0, "context": "import"}, {"source": "migration_meta_pages", "target": "ref_components_scroll_shadow", "relation": "extends", "confidence": "EXTRACTED", "source_file": "C:\\Coding\\TheDanniCraft-clipify\\.heroui-docs\\migration\\meta.json", "source_location": "L6", "weight": 1.0, "context": "import"}, {"source": "migration_meta_pages", "target": "ref_components_select", "relation": "extends", "confidence": "EXTRACTED", "source_file": "C:\\Coding\\TheDanniCraft-clipify\\.heroui-docs\\migration\\meta.json", "source_location": "L6", "weight": 1.0, "context": "import"}, {"source": "migration_meta_pages", "target": "ref_components_skeleton", "relation": "extends", "confidence": "EXTRACTED", "source_file": "C:\\Coding\\TheDanniCraft-clipify\\.heroui-docs\\migration\\meta.json", "source_location": "L6", "weight": 1.0, "context": "import"}, {"source": "migration_meta_pages", "target": "ref_components_slider", "relation": "extends", "confidence": "EXTRACTED", "source_file": "C:\\Coding\\TheDanniCraft-clipify\\.heroui-docs\\migration\\meta.json", "source_location": "L6", "weight": 1.0, "context": "import"}, {"source": "migration_meta_pages", "target": "ref_components_snippet", "relation": "extends", "confidence": "EXTRACTED", "source_file": "C:\\Coding\\TheDanniCraft-clipify\\.heroui-docs\\migration\\meta.json", "source_location": "L6", "weight": 1.0, "context": "import"}, {"source": "migration_meta_pages", "target": "ref_components_spacer", "relation": "extends", "confidence": "EXTRACTED", "source_file": "C:\\Coding\\TheDanniCraft-clipify\\.heroui-docs\\migration\\meta.json", "source_location": "L6", "weight": 1.0, "context": "import"}, {"source": "migration_meta_pages", "target": "ref_components_spinner", "relation": "extends", "confidence": "EXTRACTED", "source_file": "C:\\Coding\\TheDanniCraft-clipify\\.heroui-docs\\migration\\meta.json", "source_location": "L6", "weight": 1.0, "context": "import"}, {"source": "migration_meta_pages", "target": "ref_components_switch", "relation": "extends", "confidence": "EXTRACTED", "source_file": "C:\\Coding\\TheDanniCraft-clipify\\.heroui-docs\\migration\\meta.json", "source_location": "L6", "weight": 1.0, "context": "import"}, {"source": "migration_meta_pages", "target": "ref_components_table", "relation": "extends", "confidence": "EXTRACTED", "source_file": "C:\\Coding\\TheDanniCraft-clipify\\.heroui-docs\\migration\\meta.json", "source_location": "L6", "weight": 1.0, "context": "import"}, {"source": "migration_meta_pages", "target": "ref_components_tabs", "relation": "extends", "confidence": "EXTRACTED", "source_file": "C:\\Coding\\TheDanniCraft-clipify\\.heroui-docs\\migration\\meta.json", "source_location": "L6", "weight": 1.0, "context": "import"}, {"source": "migration_meta_pages", "target": "ref_components_toast", "relation": "extends", "confidence": "EXTRACTED", "source_file": "C:\\Coding\\TheDanniCraft-clipify\\.heroui-docs\\migration\\meta.json", "source_location": "L6", "weight": 1.0, "context": "import"}, {"source": "migration_meta_pages", "target": "ref_components_tooltip", "relation": "extends", "confidence": "EXTRACTED", "source_file": "C:\\Coding\\TheDanniCraft-clipify\\.heroui-docs\\migration\\meta.json", "source_location": "L6", "weight": 1.0, "context": "import"}, {"source": "migration_meta_pages", "target": "ref_components_user", "relation": "extends", "confidence": "EXTRACTED", "source_file": "C:\\Coding\\TheDanniCraft-clipify\\.heroui-docs\\migration\\meta.json", "source_location": "L6", "weight": 1.0, "context": "import"}]}